CHANGES.txt
MANIFEST.in
README.md
precursor.py
setup.py
precursor.egg-info/PKG-INFO
precursor.egg-info/SOURCES.txt
precursor.egg-info/dependency_links.txt
precursor.egg-info/requires.txt
precursor.egg-info/top_level.txt
src/__init__.py
src/query.py
src/sbml.py
src/utils.py
src/encodings/automatic_pseed.lp
src/encodings/card_min_precursor.lp
src/encodings/heuristic.lp
src/encodings/min_precursor.lp
src/encodings/precursor.lp
src/encodings/satcheck_precursor.lp