Metadata-Version: 2.1
Name: precursor
Version: 1.2.4
Summary: Compute minimal metabolic precursors sets that enable the production of target metabolites.
Home-page: http://bioasp.github.io/precursor/
Author: Sven Thiele
Author-email: sthiele78@gmail.com
License: GPLv3+
Platform: UNKNOWN
